<?xml version="1.0" encoding="UTF-8"?>
<?xml-stylesheet href="./bahnhof.xsl" type="text/xsl"?>
<!DOCTYPE bahnhof SYSTEM "./bahnhof.dtd">

<bahnhof>
  <name>Anschluss Brauerei Mommelbräu</name>
  <kuerzel>ABM</kuerzel>
  <typ>Anst</typ>
  <verwaltung>DR</verwaltung>
  <maszstab>120</maszstab>
  <modulnr>HaSan377</modulnr>
  <plan src="abm.jpeg" />
  <gleise>
    <zulaufstrecken>
      <links nr="1">1gl</links>
      <rechts nr="1">1gl</rechts>
    </zulaufstrecken>
    <hgleise>
      <gleis id="gleis_Streckengleis">
        <name>Streckengleis</name>
        <laenge>900</laenge>
      </gleis>
    </hgleise>
    <ngleise>
      <gleis id="gleis_1">
        <name>1</name>
        <laenge>320</laenge>
        <bemerkung>Rampengleis Abfüllung und Freirampe</bemerkung>
      </gleis>
      <gleis id="gleis_WDS">
        <name>WDS</name>
        <laenge>90</laenge>
        <bemerkung>Waggondrehscheibe, bei Bedienung Kühlhaus maximaler Achsstand 85 mm</bemerkung>
      </gleis>
      <gleis id="gleis_1a">
        <name>1a</name>
        <laenge>100</laenge>
        <bemerkung>Getreideentladung</bemerkung>
      </gleis>
      <gleis id="gleis_2">
        <name>2</name>
        <laenge>175</laenge>
        <bemerkung>Verladegleis Kühlhaus</bemerkung>
      </gleis>
    </ngleise>
  </gleise>
  <gv>
    <ladestelle id="K_hlhaus" gleis="gleis_2">
      <name>Kühlhaus</name>
      <laenge>150</laenge>
    </ladestelle>
    <ladestelle id="Getreideentladung" gleis="gleis_1a">
      <name>Getreideentladung</name>
      <laenge>100</laenge>
    </ladestelle>
    <ladestelle id="Rampe" gleis="gleis_1">
      <name>Rampe</name>
      <laenge>250</laenge>
    </ladestelle>
    <verlader>
      <name>Brauerei Mommelbräu</name>
      <empfang>
        <ladegut ladestelle="Rampe">
          <name>Hefe</name>
          <gattung>G, H</gattung>
          <wagen>1</wagen>
        </ladegut>
        <ladegut ladestelle="Rampe">
          <name>Hopfen, gesackt</name>
          <gattung>G, H</gattung>
          <wagen>2</wagen>
        </ladegut>
        <ladegut ladestelle="Rampe">
          <name>Malz, gesackt</name>
          <gattung>G, H</gattung>
          <wagen>4</wagen>
        </ladegut>
        <ladegut ladestelle="Getreideentladung">
          <name>Gerste</name>
          <gattung>G, T nur zweiachsig</gattung>
          <wagen>3</wagen>
        </ladegut>
        <ladegut ladestelle="Rampe">
          <name>Leergut - Flaschen</name>
          <gattung>G, H</gattung>
          <wagen>5</wagen>
        </ladegut>
        <ladegut ladestelle="Rampe">
          <name>Leergut - Fässer</name>
          <gattung>G, H, E, K</gattung>
          <wagen>5</wagen>
        </ladegut>
        <ladegut ladestelle="Rampe">
          <name>Etiketten</name>
          <gattung>G, H</gattung>
          <wagen>0.5</wagen>
        </ladegut>
        <ladegut ladestelle="Rampe">
          <name>Klebstoff</name>
          <gattung>G, H, Z</gattung>
          <wagen>0.5</wagen>
        </ladegut>
        <ladegut ladestelle="Rampe">
          <name>Natronlauge</name>
          <gattung>Z</gattung>
          <wagen>1</wagen>
        </ladegut>
        <ladegut ladestelle="Rampe">
          <name>Maschinenteile</name>
          <gattung>G, K</gattung>
          <wagen>0.1</wagen>
        </ladegut>
        <ladegut ladestelle="Rampe">
          <name>Paletten</name>
          <gattung>G, E, K</gattung>
          <wagen>1</wagen>
        </ladegut>
        <ladegut ladestelle="Rampe">
          <name>Feinblech für Kronkorken</name>
          <gattung>G, K, T</gattung>
          <wagen>1</wagen>
        </ladegut>
      </empfang>
      <versand>
        <ladegut ladestelle="K_hlhaus">
          <name>Bier</name>
          <gattung>I</gattung>
          <wagen>7</wagen>
        </ladegut>
        <ladegut ladestelle="Rampe">
          <name>Fassbier</name>
          <gattung>G, H, I</gattung>
          <wagen>10</wagen>
        </ladegut>
      </versand>
    </verlader>
  </gv>
  <bemerkung>Anschlussstelle ist mit Gleissperre gesichert[br]Waggondrehscheibe darf von Rangierlok befahren werden[br]Verladepunkt Kühlhaus wird über Spill bedient[br][br]Bedienung Weiche und Steuerung Waggondrehscheibe beidseitig möglich</bemerkung>
</bahnhof>

